{"36": {"note": "C", "octave": 3}, "37": {"note": "C#", "octave": 3}, "38": {"note": "D", "octave": 3}, "39": {"note": "D#", "octave": 3}, "40": {"note": "E", "octave": 3}, "41": {"note": "F", "octave": 3}, "42": {"note": "F#", "octave": 3}, "43": {"note": "G", "octave": 3}, "44": {"note": "G#", "octave": 3}, "45": {"note": "A", "octave": 3}, "46": {"note": "A#", "octave": 3}, "47": {"note": "B", "octave": 3}, "48": {"note": "C", "octave": 4}, "49": {"note": "C#", "octave": 4}, "50": {"note": "D", "octave": 4}, "51": {"note": "D#", "octave": 4}, "52": {"note": "E", "octave": 4}, "53": {"note": "F", "octave": 4}, "54": {"note": "F#", "octave": 4}, "55": {"note": "G", "octave": 4}, "56": {"note": "G#", "octave": 4}, "57": {"note": "A", "octave": 4}, "58": {"note": "A#", "octave": 4}, "59": {"note": "B", "octave": 4}, "60": {"note": "C", "octave": 5}, "61": {"note": "C#", "octave": 5}, "62": {"note": "D", "octave": 5}, "63": {"note": "D#", "octave": 5}, "64": {"note": "E", "octave": 5}, "65": {"note": "F", "octave": 5}, "66": {"note": "F#", "octave": 5}, "67": {"note": "G", "octave": 5}, "68": {"note": "G#", "octave": 5}, "69": {"note": "A", "octave": 5}, "70": {"note": "A#", "octave": 5}, "71": {"note": "B", "octave": 5}, "72": {"note": "C", "octave": 6}, "73": {"note": "C#", "octave": 6}, "74": {"note": "D", "octave": 6}, "75": {"note": "D#", "octave": 6}, "76": {"note": "E", "octave": 6}, "77": {"note": "F", "octave": 6}, "78": {"note": "F#", "octave": 6}, "79": {"note": "G", "octave": 6}, "80": {"note": "G#", "octave": 6}, "81": {"note": "A", "octave": 6}, "82": {"note": "A#", "octave": 6}, "83": {"note": "B", "octave": 6}, "84": {"note": "C", "octave": 7}}